DEBtoolPyIF/__init__.py
DEBtoolPyIF/data_sources/__init__.py
DEBtoolPyIF/data_sources/base.py
DEBtoolPyIF/data_sources/collection.py
DEBtoolPyIF/data_sources/group.py
DEBtoolPyIF/data_sources/individual.py
DEBtoolPyIF/estimation/__init__.py
DEBtoolPyIF/estimation/problem.py
DEBtoolPyIF/estimation/runner.py
DEBtoolPyIF/estimation/wrapper.py
DEBtoolPyIF/multitier/__init__.py
DEBtoolPyIF/multitier/parsers.py
DEBtoolPyIF/multitier/procedure.py
DEBtoolPyIF/notebook/__init__.py
DEBtoolPyIF/notebook/multitier_visualizers.py
DEBtoolPyIF/utils/__init__.py
DEBtoolPyIF/utils/data_formatter.py
DEBtoolPyIF-0.0.5.dist-info/LICENSE
DEBtoolPyIF-0.0.5.dist-info/METADATA
DEBtoolPyIF-0.0.5.dist-info/WHEEL
DEBtoolPyIF-0.0.5.dist-info/top_level.txt
DEBtoolPyIF-0.0.5.dist-info/RECORD
