Metadata-Version: 2.1
Name: DEBtoolPyIF
Version: 0.0.5
Summary: A Python Interface for the MATLAB package DEBtool, a package with tools for Dynamic Energy Budget models.
Author-email: "Diogo F. Oliveira" <diogo.miguel.oliveira@tecnico.ulisboa.pt>
License: MIT License
Project-URL: Homepage, https://gixthub.com/diogo-f-oliveira/DEBtool-Python-Interface
Project-URL: Issues, https://github.com/diogo-f-oliveira/DEBtool-Python-Interface/issues
Keywords: Dynamic Energy Budget,DEB,DEBtool
Classifier: Development Status :: 2 - Pre-Alpha
Classifier: Intended Audience :: Science/Research
Classifier: License :: OSI Approved :: MIT License
Classifier: Programming Language :: Python :: 3
Classifier: Topic :: Scientific/Engineering :: Bio-Informatics
Requires-Python: >=3.8
License-File: LICENSE
Requires-Dist: numpy <=1.26.4
Requires-Dist: pandas >=1.2.0
Requires-Dist: tabulate >=0.9.0
Requires-Dist: setuptools >=70.0.0
